intent_inference/__init__.py
intent_inference/api.py
intent_inference/compute/__init__.py
intent_inference/compute/dbscan.py
intent_inference/compute/isolationforest_outlier.py
intent_inference/compute/kmeans_cluster.py
intent_inference/compute/pareto.py
intent_inference/compute/range.py
intent_inference/compute/regression.py
intent_inference/inference/__init__.py
intent_inference/inference/algorithms/DBScanCluster.py
intent_inference/inference/algorithms/DBScanOutlier.py
intent_inference/inference/algorithms/IsolationForestOutlier.py
intent_inference/inference/algorithms/KMeansCluster.py
intent_inference/inference/algorithms/LinearRegression.py
intent_inference/inference/algorithms/PolynomialRegression.py
intent_inference/inference/algorithms/Skyline.py
intent_inference/inference/algorithms/base.py
intent_inference/inference/inference.py
intent_inference/inference/intent.py
intent_inference/inference/prediction.py
intent_inference/scalers/robust/__init__.py
intent_inference/tests/data/cluster_simple_v1.csv
intent_inference/tests/test_intent.py
intent_inference/utils/__init__.py
intent_inference/utils/consts.py
intent_inference-0.3.1.dist-info/LICENSE
intent_inference-0.3.1.dist-info/METADATA
intent_inference-0.3.1.dist-info/WHEEL
intent_inference-0.3.1.dist-info/RECORD
